{
  "id": "bac7d913-6e5d-4308-a701-585052011d11",
  "prevId": "00000000-0000-0000-0000-000000000000",
  "version": "7",
  "dialect": "postgresql",
  "tables": {
    "public.license_key": {
      "name": "license_key",
      "schema": "",
      "columns": {
        "id": {
          "name": "id",
          "type": "integer",
          "primaryKey": true,
          "notNull": true,
          "identity": {
            "type": "always",
            "name": "license_key_id_seq",
            "schema": "public",
            "increment": "1",
            "startWith": "1",
            "minValue": "1",
            "maxValue": "2147483647",
            "cache": "1",
            "cycle": false
          }
        },
        "key": {
          "name": "key",
          "type": "varchar(255)",
          "primaryKey": false,
          "notNull": true
        },
        "mod": {
          "name": "mod",
          "type": "varchar(32)",
          "primaryKey": false,
          "notNull": true,
          "default": "'nhnse'"
        },
        "description": {
          "name": "description",
          "type": "text",
          "primaryKey": false,
          "notNull": false
        },
        "status": {
          "name": "status",
          "type": "license_key_status",
          "typeSchema": "public",
          "primaryKey": false,
          "notNull": true,
          "default": "'active'"
        },
        "policy": {
          "name": "policy",
          "type": "license_key_policy",
          "typeSchema": "public",
          "primaryKey": false,
          "notNull": true,
          "default": "'key'"
        },
        "expiresAt": {
          "name": "expiresAt",
          "type": "timestamp",
          "primaryKey": false,
          "notNull": false
        },
        "createdAt": {
          "name": "createdAt",
          "type": "timestamp",
          "primaryKey": false,
          "notNull": true,
          "default": "now()"
        },
        "updatedAt": {
          "name": "updatedAt",
          "type": "timestamp",
          "primaryKey": false,
          "notNull": true,
          "default": "now()"
        }
      },
      "indexes": {},
      "foreignKeys": {},
      "compositePrimaryKeys": {},
      "uniqueConstraints": {
        "license_key_key_unique": {
          "name": "license_key_key_unique",
          "nullsNotDistinct": false,
          "columns": [
            "key"
          ]
        }
      },
      "policies": {},
      "checkConstraints": {},
      "isRLSEnabled": false
    },
    "public.server": {
      "name": "server",
      "schema": "",
      "columns": {
        "id": {
          "name": "id",
          "type": "integer",
          "primaryKey": true,
          "notNull": true,
          "identity": {
            "type": "always",
            "name": "server_id_seq",
            "schema": "public",
            "increment": "1",
            "startWith": "1",
            "minValue": "1",
            "maxValue": "2147483647",
            "cache": "1",
            "cycle": false
          }
        },
        "licenseKeyId": {
          "name": "licenseKeyId",
          "type": "integer",
          "primaryKey": false,
          "notNull": true
        },
        "ip": {
          "name": "ip",
          "type": "varchar(64)",
          "primaryKey": false,
          "notNull": false
        },
        "hostname": {
          "name": "hostname",
          "type": "varchar(191)",
          "primaryKey": false,
          "notNull": false
        },
        "map": {
          "name": "map",
          "type": "varchar(64)",
          "primaryKey": false,
          "notNull": false
        },
        "players": {
          "name": "players",
          "type": "integer",
          "primaryKey": false,
          "notNull": true,
          "default": 0
        },
        "maxplayers": {
          "name": "maxplayers",
          "type": "integer",
          "primaryKey": false,
          "notNull": true,
          "default": 0
        },
        "version": {
          "name": "version",
          "type": "varchar(64)",
          "primaryKey": false,
          "notNull": false
        },
        "lastSeenAt": {
          "name": "lastSeenAt",
          "type": "timestamp",
          "primaryKey": false,
          "notNull": true,
          "default": "now()"
        },
        "createdAt": {
          "name": "createdAt",
          "type": "timestamp",
          "primaryKey": false,
          "notNull": true,
          "default": "now()"
        }
      },
      "indexes": {},
      "foreignKeys": {
        "server_licenseKeyId_license_key_id_fk": {
          "name": "server_licenseKeyId_license_key_id_fk",
          "tableFrom": "server",
          "tableTo": "license_key",
          "columnsFrom": [
            "licenseKeyId"
          ],
          "columnsTo": [
            "id"
          ],
          "onDelete": "cascade",
          "onUpdate": "no action"
        }
      },
      "compositePrimaryKeys": {},
      "uniqueConstraints": {
        "server_licenseKeyId_unique": {
          "name": "server_licenseKeyId_unique",
          "nullsNotDistinct": false,
          "columns": [
            "licenseKeyId"
          ]
        }
      },
      "policies": {},
      "checkConstraints": {},
      "isRLSEnabled": false
    },
    "public.user": {
      "name": "user",
      "schema": "",
      "columns": {
        "id": {
          "name": "id",
          "type": "integer",
          "primaryKey": true,
          "notNull": true,
          "identity": {
            "type": "always",
            "name": "user_id_seq",
            "schema": "public",
            "increment": "1",
            "startWith": "1",
            "minValue": "1",
            "maxValue": "2147483647",
            "cache": "1",
            "cycle": false
          }
        },
        "username": {
          "name": "username",
          "type": "varchar(255)",
          "primaryKey": false,
          "notNull": true
        },
        "age": {
          "name": "age",
          "type": "integer",
          "primaryKey": false,
          "notNull": true
        },
        "role": {
          "name": "role",
          "type": "user_role",
          "typeSchema": "public",
          "primaryKey": false,
          "notNull": true,
          "default": "'user'"
        },
        "email": {
          "name": "email",
          "type": "varchar(255)",
          "primaryKey": false,
          "notNull": false
        },
        "passwordHash": {
          "name": "passwordHash",
          "type": "varchar",
          "primaryKey": false,
          "notNull": true
        },
        "createdAt": {
          "name": "createdAt",
          "type": "timestamp",
          "primaryKey": false,
          "notNull": true,
          "default": "now()"
        },
        "updatedAt": {
          "name": "updatedAt",
          "type": "timestamp",
          "primaryKey": false,
          "notNull": true,
          "default": "now()"
        }
      },
      "indexes": {},
      "foreignKeys": {},
      "compositePrimaryKeys": {},
      "uniqueConstraints": {
        "user_username_unique": {
          "name": "user_username_unique",
          "nullsNotDistinct": false,
          "columns": [
            "username"
          ]
        },
        "user_email_unique": {
          "name": "user_email_unique",
          "nullsNotDistinct": false,
          "columns": [
            "email"
          ]
        }
      },
      "policies": {},
      "checkConstraints": {},
      "isRLSEnabled": false
    }
  },
  "enums": {
    "public.license_key_policy": {
      "name": "license_key_policy",
      "schema": "public",
      "values": [
        "key",
        "time",
        "open"
      ]
    },
    "public.license_key_status": {
      "name": "license_key_status",
      "schema": "public",
      "values": [
        "active",
        "inactive"
      ]
    },
    "public.user_role": {
      "name": "user_role",
      "schema": "public",
      "values": [
        "user",
        "admin"
      ]
    }
  },
  "schemas": {},
  "sequences": {},
  "roles": {},
  "policies": {},
  "views": {},
  "_meta": {
    "columns": {},
    "schemas": {},
    "tables": {}
  }
}